schemastore/__init__.py
schemastore/__main__.py
schemastore/cache.sqlite
schemastore/py.typed
schemastore/tests/__init__.py
schemastore/tests/test_jsonschema.py
schemastore-0.2.2.dist-info/METADATA
schemastore-0.2.2.dist-info/WHEEL
schemastore-0.2.2.dist-info/licenses/LICENSE
schemastore-0.2.2.dist-info/RECORD
