Metadata-Version: 2.4
Name: schemastore
Version: 0.2.2
Summary: Easy use of the JSON SchemaStore from Python, as a referencing.Registry
Project-URL: Homepage, https://github.com/python-jsonschema/schemastore
Project-URL: Issues, https://github.com/python-jsonschema/schemastore/issues/
Project-URL: Source, https://github.com/python-jsonschema/schemastore
Author-email: Sorin Sbarnea <sorin.sbarnea@gmail.com>, Julian Berman <Julian+SchemaStore@GrayVines.com>
License-File: LICENSE
Keywords: json,jsonschema,referencing,schemas,schemastore,yaml
Classifier: Development Status :: 4 - Beta
Classifier: Intended Audience :: Developers
Classifier: License :: OSI Approved :: Apache Software License
Classifier: Operating System :: OS Independent
Classifier: Programming Language :: Python
Classifier: Programming Language :: Python :: 3.9
Classifier: Programming Language :: Python :: 3.10
Classifier: Programming Language :: Python :: 3.11
Classifier: Programming Language :: Python :: 3.12
Classifier: Programming Language :: Python :: 3.13
Classifier: Programming Language :: Python :: Implementation :: CPython
Classifier: Programming Language :: Python :: Implementation :: PyPy
Classifier: Topic :: File Formats :: JSON
Classifier: Topic :: File Formats :: JSON :: JSON Schema
Requires-Python: >=3.8
Requires-Dist: referencing
Requires-Dist: requests-cache>=1.0.0a0
